clickzetta_zettapark_python-1.13.0-py3.8-nspkg.pth
clickzetta/zettapark/__init__.py
clickzetta/zettapark/_adaptor.py
clickzetta/zettapark/async_job.py
clickzetta/zettapark/column.py
clickzetta/zettapark/context.py
clickzetta/zettapark/dataframe.py
clickzetta/zettapark/dataframe_analytics_functions.py
clickzetta/zettapark/dataframe_na_functions.py
clickzetta/zettapark/dataframe_reader.py
clickzetta/zettapark/dataframe_stat_functions.py
clickzetta/zettapark/dataframe_writer.py
clickzetta/zettapark/exceptions.py
clickzetta/zettapark/file_operation.py
clickzetta/zettapark/files.py
clickzetta/zettapark/functions.py
clickzetta/zettapark/py.typed
clickzetta/zettapark/query_history.py
clickzetta/zettapark/relational_grouped_dataframe.py
clickzetta/zettapark/row.py
clickzetta/zettapark/session.py
clickzetta/zettapark/stored_procedure.py
clickzetta/zettapark/table.py
clickzetta/zettapark/table_function.py
clickzetta/zettapark/types.py
clickzetta/zettapark/udaf.py
clickzetta/zettapark/udf.py
clickzetta/zettapark/udtf.py
clickzetta/zettapark/version.py
clickzetta/zettapark/window.py
clickzetta/zettapark/_internal/__init__.py
clickzetta/zettapark/_internal/code_generation.py
clickzetta/zettapark/_internal/df_pandas_utils.py
clickzetta/zettapark/_internal/error_message.py
clickzetta/zettapark/_internal/packaging_utils.py
clickzetta/zettapark/_internal/server_connection.py
clickzetta/zettapark/_internal/telemetry.py
clickzetta/zettapark/_internal/type_utils.py
clickzetta/zettapark/_internal/udf_utils.py
clickzetta/zettapark/_internal/utils.py
clickzetta/zettapark/_internal/volume_utils.py
clickzetta/zettapark/_internal/analyzer/__init__.py
clickzetta/zettapark/_internal/analyzer/analyzer.py
clickzetta/zettapark/_internal/analyzer/analyzer_utils.py
clickzetta/zettapark/_internal/analyzer/binary_expression.py
clickzetta/zettapark/_internal/analyzer/binary_plan_node.py
clickzetta/zettapark/_internal/analyzer/cte_utils.py
clickzetta/zettapark/_internal/analyzer/datatype_mapper.py
clickzetta_zettapark_python-1.13.0.dist-info/LICENSE
clickzetta_zettapark_python-1.13.0.dist-info/LICENSE.txt
clickzetta_zettapark_python-1.13.0.dist-info/METADATA
clickzetta_zettapark_python-1.13.0.dist-info/WHEEL
clickzetta_zettapark_python-1.13.0.dist-info/namespace_packages.txt
clickzetta_zettapark_python-1.13.0.dist-info/top_level.txt
clickzetta_zettapark_python-1.13.0.dist-info/RECORD
